automap.cpython-310-darwin.so
automap-0.6.1.dist-info/LICENSE.md
automap-0.6.1.dist-info/METADATA
automap-0.6.1.dist-info/WHEEL
automap-0.6.1.dist-info/top_level.txt
automap-0.6.1.dist-info/RECORD
