Metadata-Version: 2.1
Name: automap
Version: 0.6.1
Summary: High-performance autoincremented integer-valued mappings.
Home-page: https://github.com/brandtbucher/automap
Author: Brandt Bucher
Author-email: brandt@python.org
License: MIT
Requires-Python: >=3.7.0
License-File: LICENSE.md
